functions/__init__.py
functions/utils.py
pyeca-0.0.1.dist-info/LICENSE
pyeca-0.0.1.dist-info/METADATA
pyeca-0.0.1.dist-info/WHEEL
pyeca-0.0.1.dist-info/top_level.txt
pyeca-0.0.1.dist-info/RECORD
