Metadata-Version: 2.1
Name: pyeca
Version: 0.0.1
Summary: ECA Functions
Home-page: UNKNOWN
Author: John Viloria Amaris
Author-email: jviloriaa-est@electricaribe.co
License: MIT
Platform: UNKNOWN
Requires-Dist: pathlib
Requires-Dist: datetime
